botifyme/__init__.py
botifyme/__main__.py
botifyme/agent.py
botifyme/cli/__init__.py
botifyme/config.py
botifyme/registry.py
botifyme/runtime.py
botifyme/tasks/__init__.py
botifyme/tasks/task.py
botifyme/utils/__init__.py
botifyme/utils/tools.py
botifyme/workflow.py
botifyme-0.1.5.2.dist-info/LICENSE
botifyme-0.1.5.2.dist-info/METADATA
botifyme-0.1.5.2.dist-info/WHEEL
botifyme-0.1.5.2.dist-info/entry_points.txt
botifyme-0.1.5.2.dist-info/RECORD
